pydecorator/__init__.py
pydecorator/file.py
pydecorator/generator.py
pydecorator/numpy.py
pydecorator/pandas.py
pydecorator/sort.py
pydecorator/transform.py
pydecorator/util.py
pydecorator-1.0.dist-info/LICENSE
pydecorator-1.0.dist-info/METADATA
pydecorator-1.0.dist-info/WHEEL
pydecorator-1.0.dist-info/top_level.txt
pydecorator-1.0.dist-info/RECORD
