Metadata-Version: 2.1
Name: pydecorator
Version: 1.0
Summary: Python Decorator Functions
Home-page: https://github.com/luciancooper/pydecorator
Author: Lucian Cooper
License: MIT
Keywords: decorator utility
Platform: UNKNOWN
Classifier: Intended Audience :: Developers
Classifier: License :: OSI Approved :: MIT License
Classifier: Programming Language :: Python
Classifier: Programming Language :: Python :: 3.6
Classifier: Topic :: Software Development
Classifier: Topic :: Software Development :: Libraries :: Python Modules
Classifier: Topic :: Utilities
Requires-Dist: numpy
Requires-Dist: pandas
